management/__init__.py
management/admin.py
management/apps.py
management/authentication.py
management/consumers.py
management/forms.py
management/models.py
management/routing.py
management/urls.py
management/utils.py
management/views.py
management/management/commands/create_admin.py
management/management/commands/process_reminders.py
management/migrations/0001_initial.py
management/migrations/0002_auto_20201007_1636.py
management/migrations/__init__.py
management/static/management/css/DateTimePicker.css
management/static/management/css/style.css
management/static/management/js/DateTimePicker.js
management/static/management/js/datetime.js
management/static/management/js/session.js
management/templates/management/add_election.html
management/templates/management/add_mobile_voter_name.html
management/templates/management/add_mobile_voter_qr.html
management/templates/management/add_session.html
management/templates/management/add_tokens.html
management/templates/management/add_voters.html
management/templates/management/application.html
management/templates/management/base.html
management/templates/management/election.html
management/templates/management/help.html
management/templates/management/image_input.html
management/templates/management/import_csv.html
management/templates/management/index.html
management/templates/management/login.html
management/templates/management/results.html
management/templates/management/session.html
management/templates/management/session_election_item.html
management/templates/management/session_settings.html
management/templates/management/spectator_settings.html
vote/__init__.py
vote/admin.py
vote/apps.py
vote/authentication.py
vote/consumers.py
vote/forms.py
vote/models.py
vote/routing.py
vote/selectors.py
vote/tests.py
vote/urls.py
vote/views.py
vote/management/commands/create_election.py
vote/management/commands/create_session.py
vote/management/commands/create_voter.py
vote/management/commands/reset_voter.py
wahlfang-1.0.7.dist-info/LICENSE
wahlfang-1.0.7.dist-info/METADATA
wahlfang-1.0.7.dist-info/WHEEL
wahlfang-1.0.7.dist-info/entry_points.txt
wahlfang-1.0.7.dist-info/top_level.txt
wahlfang-1.0.7.dist-info/RECORD
