Metadata-Version: 2.1
Name: wahlfang
Version: 1.0.7
Summary: Wahlfang - a simple, feature complete online voting platform.
Home-page: https://gitlab.stusta.de/stustanet/wahlfang
Author: StuStaNet e. V.
Author-email: admins@stustanet.de
License: MIT
Classifier: Operating System :: OS Independent
Classifier: Programming Language :: Python :: 3
Classifier: License :: OSI Approved :: MIT License
Classifier: Topic :: Internet :: WWW/HTTP :: WSGI :: Application
Classifier: Development Status :: 4 - Beta
Classifier: Framework :: Django
Requires-Python: >=3.6
License-File: LICENSE
Requires-Dist: Django (~=3.2)
Requires-Dist: django-crispy-forms (~=1.11)
Requires-Dist: django-csp (~=3.7)
Requires-Dist: django-ratelimit (~=3.0)
Requires-Dist: pillow (~=8.2)
Requires-Dist: argon2-cffi (~=20.1)
Requires-Dist: django-auth-ldap (~=2.4)
Requires-Dist: qrcode (~=6.1)
Requires-Dist: latex (~=0.7)
Requires-Dist: django-prometheus (~=2.1)
Requires-Dist: channels (~=3.0)
Requires-Dist: channels-redis (~=3.2)
Requires-Dist: djangorestframework (~=3.12)
Requires-Dist: djangorestframework-simplejwt (~=4.7)
